pycoinlib/__init__.py
pycoinlib/client.py
pycoinlib-0.2.dist-info/LICENSE
pycoinlib-0.2.dist-info/METADATA
pycoinlib-0.2.dist-info/WHEEL
pycoinlib-0.2.dist-info/top_level.txt
pycoinlib-0.2.dist-info/RECORD
