Metadata-Version: 2.1
Name: pycoinlib
Version: 0.2
Summary: Python client for the coinlib.io API.
Home-page: https://github.com/atkinson/pycoinlib
Author: Rich Atkinson
Author-email: rich@airteam.com.au
License: MIT License
Keywords: crypto,trading,coinlib
Platform: UNKNOWN
Classifier: Development Status :: 4 - Beta
Classifier: Intended Audience :: Developers
Classifier: Topic :: Software Development :: Libraries :: Python Modules
Classifier: License :: OSI Approved :: MIT License
Classifier: Programming Language :: Python :: 3.9
Requires-Dist: requests
